setup.py
folumo/__init__.py
folumo.egg-info/PKG-INFO
folumo.egg-info/SOURCES.txt
folumo.egg-info/dependency_links.txt
folumo.egg-info/requires.txt
folumo.egg-info/top_level.txt
folumo/betterGUI/__init__.py
folumo/betterGUI/basicElements.py
folumo/betterGUI/constants.py
folumo/betterGUI/screen.py
folumo/betterGUI/Game/__init__.py
folumo/betterGUI/Game/toolbox.py
folumo/betterGUI/UI/__init__.py
folumo/betterGUI/UI/toolbox.py
folumo/config/__init__.py
folumo/func/__init__.py