Metadata-Version: 2.1
Name: folumo
Version: 0.1.9.3
Summary: Multipurpose lib
Home-page: UNKNOWN
Author: Folumo (Ominox_)
Author-email: <ominox_@folumo.com>
License: UNKNOWN
Keywords: python,gui,app,game
Platform: UNKNOWN
Classifier: Intended Audience :: Developers
Classifier: Programming Language :: Python :: 3
Classifier: Operating System :: Microsoft :: Windows
